{
  "__inputs": [],
  "__requires": [],
  "title": "Infrastructure Health",
  "uid": "infra-health",
  "panels": [
    {
      "title": "Ticker Activity",
      "type": "table",
      "gridPos": {"x": 0, "y": 0, "w": 24, "h": 8},
      "targets": [
        {"expr": "idx_messages_sent_total", "legendFormat": "{{ticker}}"}
      ]
    },
    {
      "title": "System Status",
      "type": "text",
      "gridPos": {"x": 0, "y": 8, "w": 24, "h": 4},
      "content": "## Pipeline Status\n\nProducer metrics available at http://localhost:8000/metrics\n\nPrometheus: http://localhost:9090\n\nGrafana: http://localhost:3000",
      "mode": "markdown"
    }
  ],
  "schemaVersion": 27,
  "version": 1
}
